{
  "cluster_map": "[3, 3, 0, 0, 0, 0, 0, 0, 0, 0, 0, 0, 0, 0, 4, 4, 3, 3, 0, 0, 0, 0, 0, 0, 0, 0, 0, 0, 0, 0, 4, 4, 3, 3, 0, 0, 0, 0, 0, 0, 0, 0, 0, 0, 0, 0, 0, 0, 3, 3, 0, 0, 0, 0, 0, 0, 0, 0, 0, 0, 0, 0, 0, 0, 6, 6, 0, 0, 0, 0, 0, 0, 0, 0, 0, 0, 0, 0, 0, 0, 6, 6, 0, 0, 0, 0, 0, 0, 0, 0, 0, 0, 0, 0, 0, 0, 6, 6, 0, 0, 0, 0, 0, 0, 0, 0, 0, 0, 0, 0, 0, 0, 6, 6, 0, 0, 0, 0, 0, 0, 0, 0, 0, 0, 0, 0, 0, 0, 5, 5, 0, 0, 0, 0, 0, 0, 0, 0, 0, 0, 0, 0, 0, 0, 0, 5, 0, 0, 0, 0, 0, 0, 0, 0, 0, 0, 0, 0, 0, 0, 0, 0, 0, 0, 0, 0, 0, 0, 0, 0, 0, 0, 0, 0, 0, 0, 0, 0, 0, 0, 0, 0, 0, 0, 0, 0, 0, 0, 0, 0, 0, 0, 0, 0, 0, 0, 0, 0, 0, 0, 0, 0, 0, 0, 0, 0, 0, 0, 2, 2, 0, 0, 0, 0, 0, 0, 0, 0, 0, 0, 0, 0, 0, 0, 2, 2, 0, 0, 0, 0, 0, 0, 0, 0, 0, 0, 0, 0, 1, 1, 2, 2, 0, 0, 0, 0, 0, 0, 0, 0, 0, 0, 0, 0, 1, 1]",
  "group_name": "binniecore\\assets\\extratrees\\textures\\blocks\\glass\\thicktsection.1.png",
  "segment_dicts": [
    {
      "hues": [
        0.6666666666666666
      ],
      "lightness": 1.0,
      "sats": [
        1.0
      ],
      "vals": [
        1.0
      ],
      "variance": 0.16308301363396954
    },
    {
      "hues": [
        0.6666666666666666
      ],
      "lightness": 1.0,
      "sats": [
        1.0
      ],
      "vals": [
        1.0
      ],
      "variance": 0.12401959270615269
    },
    {
      "hues": [
        0.6666666666666666
      ],
      "lightness": 1.0,
      "sats": [
        1.0
      ],
      "vals": [
        1.0
      ],
      "variance": 0.15128841196122722
    },
    {
      "hues": [
        0.6666666666666666
      ],
      "lightness": 1.0,
      "sats": [
        1.0
      ],
      "vals": [
        1.0
      ],
      "variance": 0.17399263633843817
    },
    {
      "hues": [
        0.6666666666666666
      ],
      "lightness": 1.0,
      "sats": [
        1.0
      ],
      "vals": [
        1.0
      ],
      "variance": 0.12401959270615269
    },
    {
      "hues": [
        0.6666666666666666
      ],
      "lightness": 1.0,
      "sats": [
        1.0
      ],
      "vals": [
        1.0
      ],
      "variance": 0.10761701026528055
    },
    {
      "hues": [
        0.6666666666666666
      ],
      "lightness": 1.0,
      "sats": [
        1.0
      ],
      "vals": [
        1.0
      ],
      "variance": 0.17399263633843817
    }
  ]
}