{
  "cluster_map": "[0, 0, 0, 0, 0, 0, 0, 0, 0, 0, 0, 0, 0, 0, 0, 0, 0, 0, 0, 0, 0, 0, 0, 0, 0, 0, 0, 0, 0, 0, 0, 0, 0, 0, 0, 0, 0, 0, 0, 0, 0, 0, 3, 3, 0, 0, 0, 0, 0, 0, 0, 0, 0, 2, 1, 1, 1, 1, 3, 3, 3, 2, 0, 0, 0, 0, 0, 2, 2, 2, 1, 1, 1, 1, 3, 3, 3, 2, 2, 0, 0, 0, 0, 1, 1, 1, 1, 1, 1, 1, 3, 3, 3, 2, 2, 2, 2, 2, 2, 1, 1, 1, 1, 1, 1, 1, 3, 3, 3, 2, 2, 2, 2, 2, 2, 1, 1, 1, 1, 1, 1, 3, 3, 3, 3, 2, 2, 2, 2, 2, 2, 1, 1, 1, 1, 3, 3, 3, 3, 3, 3, 2, 2, 2, 2, 2, 2, 2, 2, 1, 3, 3, 3, 3, 3, 3, 3, 2, 2, 2, 2, 2, 2, 2, 2, 2, 3, 3, 3, 3, 3, 2, 2, 2, 2, 2, 0, 2, 2, 2, 2, 2, 3, 3, 3, 3, 2, 2, 2, 2, 2, 0, 0, 0, 2, 2, 2, 2, 3, 3, 3, 2, 2, 2, 2, 2, 0, 0, 0, 0, 0, 2, 2, 2, 2, 2, 2, 2, 0, 0, 0, 0, 0, 0, 0, 0, 0, 0, 0, 0, 0, 0, 0, 0, 0, 0, 0, 0, 0, 0, 0, 0, 0, 0, 0, 0, 0, 0, 0, 0, 0, 0, 0, 0, 0, 0]",
  "group_name": "witchery\\assets\\witchery\\textures\\items\\vcoffin.png",
  "segment_dicts": [
    {
      "hues": [
        0.0
      ],
      "lightness": 0.0,
      "sats": [
        0.0
      ],
      "vals": [
        0.0
      ],
      "variance": NaN
    },
    {
      "hues": [
        0.6666666666666666,
        0.0
      ],
      "lightness": 0.25323826500297086,
      "sats": [
        1.0,
        0.0
      ],
      "vals": [
        0.0,
        0.23137254901960785,
        0.2627450980392157,
        0.27450980392156865
      ],
      "variance": 0.34195867694697407
    },
    {
      "hues": [
        0.6666666666666666,
        0.0
      ],
      "lightness": 0.09008863819500404,
      "sats": [
        1.0,
        0.0
      ],
      "vals": [
        0.0,
        0.2,
        0.21568627450980393,
        0.21568627450980396,
        0.2235294117647059,
        0.23137254901960785,
        0.27450980392156865
      ],
      "variance": 0.8000385818558859
    },
    {
      "hues": [
        0.6666666666666666,
        0.0
      ],
      "lightness": 0.18850889192886455,
      "sats": [
        1.0,
        0.0
      ],
      "vals": [
        0.0,
        0.21568627450980393,
        0.23137254901960785,
        0.2627450980392157,
        0.27450980392156865
      ],
      "variance": 0.4392491500382581
    }
  ]
}